yt_dlp/YoutubeDL.py
yt_dlp/__init__.py
yt_dlp/__main__.py
yt_dlp/aes.py
yt_dlp/cache.py
yt_dlp/cookies.py
yt_dlp/jsinterp.py
yt_dlp/minicurses.py
yt_dlp/options.py
yt_dlp/plugins.py
yt_dlp/socks.py
yt_dlp/update.py
yt_dlp/version.py
yt_dlp/webvtt.py
yt_dlp/__pyinstaller/__init__.py
yt_dlp/__pyinstaller/hook-yt_dlp.py
yt_dlp/compat/__init__.py
yt_dlp/compat/_deprecated.py
yt_dlp/compat/_legacy.py
yt_dlp/compat/compat_utils.py
yt_dlp/compat/imghdr.py
yt_dlp/compat/shutil.py
yt_dlp/compat/types.py
yt_dlp/compat/urllib/__init__.py
yt_dlp/compat/urllib/request.py
yt_dlp/dependencies/Cryptodome.py
yt_dlp/dependencies/__init__.py
yt_dlp/downloader/__init__.py
yt_dlp/downloader/common.py
yt_dlp/downloader/dash.py
yt_dlp/downloader/external.py
yt_dlp/downloader/f4m.py
yt_dlp/downloader/fc2.py
yt_dlp/downloader/fragment.py
yt_dlp/downloader/hls.py
yt_dlp/downloader/http.py
yt_dlp/downloader/ism.py
yt_dlp/downloader/mhtml.py
yt_dlp/downloader/niconico.py
yt_dlp/downloader/rtmp.py
yt_dlp/downloader/rtsp.py
yt_dlp/downloader/websocket.py
yt_dlp/downloader/youtube_live_chat.py
yt_dlp/extractor/__init__.py
yt_dlp/extractor/_extractors.py
yt_dlp/extractor/abc.py
yt_dlp/extractor/abcnews.py
yt_dlp/extractor/abcotvs.py
yt_dlp/extractor/abematv.py
yt_dlp/extractor/academicearth.py
yt_dlp/extractor/acast.py
yt_dlp/extractor/acfun.py
yt_dlp/extractor/adn.py
yt_dlp/extractor/adobeconnect.py
yt_dlp/extractor/adobepass.py
yt_dlp/extractor/adobetv.py
yt_dlp/extractor/adultswim.py
yt_dlp/extractor/aenetworks.py
yt_dlp/extractor/aeonco.py
yt_dlp/extractor/afreecatv.py
yt_dlp/extractor/agora.py
yt_dlp/extractor/airtv.py
yt_dlp/extractor/aitube.py
yt_dlp/extractor/aliexpress.py
yt_dlp/extractor/aljazeera.py
yt_dlp/extractor/allocine.py
yt_dlp/extractor/allstar.py
yt_dlp/extractor/alphaporno.py
yt_dlp/extractor/alsace20tv.py
yt_dlp/extractor/altcensored.py
yt_dlp/extractor/alura.py
yt_dlp/extractor/amadeustv.py
yt_dlp/extractor/amara.py
yt_dlp/extractor/amazon.py
slikts_yt_dlp-2025.1.26.dist-info/METADATA
slikts_yt_dlp-2025.1.26.dist-info/WHEEL
slikts_yt_dlp-2025.1.26.dist-info/entry_points.txt
slikts_yt_dlp-2025.1.26.dist-info/licenses/LICENSE
slikts_yt_dlp-2025.1.26.dist-info/RECORD
