Metadata-Version: 2.4
Name: slikts-yt-dlp
Version: 2025.1.26
Summary: A feature-rich command-line audio/video downloader
Project-URL: Documentation, https://github.com/yt-dlp/yt-dlp#readme
Project-URL: Repository, https://github.com/yt-dlp/yt-dlp
Project-URL: Tracker, https://github.com/yt-dlp/yt-dlp/issues
Project-URL: Funding, https://github.com/yt-dlp/yt-dlp/blob/master/Collaborators.md#collaborators
Maintainer-email: pukkandan <pukkandan.ytdlp@gmail.com>, Grub4K <contact@grub4k.xyz>, bashonly <bashonly@protonmail.com>, coletdjnz <coletdjnz@protonmail.com>, sepro <sepro@sepr0.com>
License: This is free and unencumbered software released into the public domain.
License-File: LICENSE
Keywords: sponsorblock,video-downloader,youtube-dl,youtube-dlc,youtube-downloader,yt-dlp
Classifier: Development Status :: 5 - Production/Stable
Classifier: Environment :: Console
Classifier: License :: OSI Approved :: The Unlicense (Unlicense)
Classifier: Operating System :: OS Independent
Classifier: Programming Language :: Python
Classifier: Programming Language :: Python :: 3 :: Only
Classifier: Programming Language :: Python :: 3.9
Classifier: Programming Language :: Python :: 3.10
Classifier: Programming Language :: Python :: 3.11
Classifier: Programming Language :: Python :: 3.12
Classifier: Programming Language :: Python :: 3.13
Classifier: Programming Language :: Python :: Implementation
Classifier: Programming Language :: Python :: Implementation :: CPython
Classifier: Programming Language :: Python :: Implementation :: PyPy
Classifier: Topic :: Multimedia :: Video
Requires-Python: >=3.9
Provides-Extra: build
Requires-Dist: build; extra == 'build'
Requires-Dist: hatchling; extra == 'build'
Requires-Dist: pip; extra == 'build'
Requires-Dist: setuptools>=71.0.2; extra == 'build'
Requires-Dist: wheel; extra == 'build'
Provides-Extra: curl-cffi
Requires-Dist: curl-cffi!=0.6.*,<0.7.2,>=0.5.10; (os_name != 'nt' and implementation_name == 'cpython') and extra == 'curl-cffi'
Requires-Dist: curl-cffi==0.5.10; (os_name == 'nt' and implementation_name == 'cpython') and extra == 'curl-cffi'
Provides-Extra: default
Requires-Dist: brotli; (implementation_name == 'cpython') and extra == 'default'
Requires-Dist: brotlicffi; (implementation_name != 'cpython') and extra == 'default'
Requires-Dist: certifi; extra == 'default'
Requires-Dist: mutagen; extra == 'default'
Requires-Dist: pycryptodomex; extra == 'default'
Requires-Dist: requests<3,>=2.32.2; extra == 'default'
Requires-Dist: urllib3<3,>=1.26.17; extra == 'default'
Requires-Dist: websockets>=13.0; extra == 'default'
Provides-Extra: dev
Requires-Dist: pre-commit; extra == 'dev'
Requires-Dist: yt-dlp[static-analysis]; extra == 'dev'
Requires-Dist: yt-dlp[test]; extra == 'dev'
Provides-Extra: pyinstaller
Requires-Dist: pyinstaller>=6.11.1; extra == 'pyinstaller'
Provides-Extra: secretstorage
Requires-Dist: cffi; extra == 'secretstorage'
Requires-Dist: secretstorage; extra == 'secretstorage'
Provides-Extra: static-analysis
Requires-Dist: autopep8~=2.0; extra == 'static-analysis'
Requires-Dist: ruff~=0.9.0; extra == 'static-analysis'
Provides-Extra: test
Requires-Dist: pytest-rerunfailures~=14.0; extra == 'test'
Requires-Dist: pytest~=8.1; extra == 'test'
